CONTRIBUTING.md
MANIFEST.in
README.rst
setup.py
docs/HISTORY.txt
docs/LICENSE.GPL
docs/LICENSE.txt
eea/__init__.py
eea.comments.egg-info/PKG-INFO
eea.comments.egg-info/SOURCES.txt
eea.comments.egg-info/dependency_links.txt
eea.comments.egg-info/entry_points.txt
eea.comments.egg-info/namespace_packages.txt
eea.comments.egg-info/not-zip-safe
eea.comments.egg-info/requires.txt
eea.comments.egg-info/top_level.txt
eea/comments/README.txt
eea/comments/__init__.py
eea/comments/configure.zcml
eea/comments/interfaces.py
eea/comments/overrides.zcml
eea/comments/permissions.zcml
eea/comments/profiles.zcml
eea/comments/setuphandlers.py
eea/comments/version.txt
eea/comments/browser/__init__.py
eea/comments/browser/configure.zcml
eea/comments/locales/__init__.py
eea/comments/locales/eea.pot
eea/comments/locales/plone-manual.pot
eea/comments/locales/update.sh
eea/comments/locales/bg/LC_MESSAGES/eea.po
eea/comments/locales/bg/LC_MESSAGES/plone.po
eea/comments/locales/cs/LC_MESSAGES/eea.po
eea/comments/locales/cs/LC_MESSAGES/plone.po
eea/comments/locales/da/LC_MESSAGES/eea.po
eea/comments/locales/da/LC_MESSAGES/plone.po
eea/comments/locales/de/LC_MESSAGES/eea.po
eea/comments/locales/de/LC_MESSAGES/plone.po
eea/comments/locales/el/LC_MESSAGES/eea.po
eea/comments/locales/el/LC_MESSAGES/plone.po
eea/comments/locales/en/LC_MESSAGES/eea.po
eea/comments/locales/en/LC_MESSAGES/plone.po
eea/comments/locales/es/LC_MESSAGES/eea.po
eea/comments/locales/es/LC_MESSAGES/plone.po
eea/comments/locales/et/LC_MESSAGES/eea.po
eea/comments/locales/et/LC_MESSAGES/plone.po
eea/comments/locales/eu/LC_MESSAGES/eea.po
eea/comments/locales/eu/LC_MESSAGES/plone.po
eea/comments/locales/fi/LC_MESSAGES/eea.po
eea/comments/locales/fi/LC_MESSAGES/plone.po
eea/comments/locales/fr/LC_MESSAGES/eea.po
eea/comments/locales/fr/LC_MESSAGES/plone.po
eea/comments/locales/hr/LC_MESSAGES/eea.po
eea/comments/locales/hr/LC_MESSAGES/plone.po
eea/comments/locales/hu/LC_MESSAGES/eea.po
eea/comments/locales/hu/LC_MESSAGES/plone.po
eea/comments/locales/is/LC_MESSAGES/eea.po
eea/comments/locales/is/LC_MESSAGES/plone.po
eea/comments/locales/it/LC_MESSAGES/eea.po
eea/comments/locales/it/LC_MESSAGES/plone.po
eea/comments/locales/kl/LC_MESSAGES/eea.po
eea/comments/locales/kl/LC_MESSAGES/plone.po
